odoo/addons/sale_order_line_move_to_optional/README.rst
odoo/addons/sale_order_line_move_to_optional/__init__.py
odoo/addons/sale_order_line_move_to_optional/__manifest__.py
odoo/addons/sale_order_line_move_to_optional/i18n/sale_order_line_move_to_optional.pot
odoo/addons/sale_order_line_move_to_optional/models/__init__.py
odoo/addons/sale_order_line_move_to_optional/models/sale_order.py
odoo/addons/sale_order_line_move_to_optional/readme/CONTRIBUTORS.md
odoo/addons/sale_order_line_move_to_optional/readme/DESCRIPTION.md
odoo/addons/sale_order_line_move_to_optional/readme/USAGE.md
odoo/addons/sale_order_line_move_to_optional/static/description/icon.png
odoo/addons/sale_order_line_move_to_optional/static/description/index.html
odoo/addons/sale_order_line_move_to_optional/tests/__init__.py
odoo/addons/sale_order_line_move_to_optional/tests/test_sale_order_line_move.py
odoo/addons/sale_order_line_move_to_optional/views/sale_order.xml
odoo_addon_sale_order_line_move_to_optional-16.0.1.0.0.2.dist-info/METADATA
odoo_addon_sale_order_line_move_to_optional-16.0.1.0.0.2.dist-info/WHEEL
odoo_addon_sale_order_line_move_to_optional-16.0.1.0.0.2.dist-info/top_level.txt
odoo_addon_sale_order_line_move_to_optional-16.0.1.0.0.2.dist-info/RECORD
