Metadata-Version: 2.1
Name: odoo-addon-sale_order_line_move_to_optional
Version: 16.0.1.0.0.2
Summary: Move sale order line to optional products.
Home-page: https://github.com/OCA/sale-workflow
Author: Nextev Srl, Odoo Community Association (OCA)
Author-email: support@odoo-community.org
License: AGPL-3
Classifier: Programming Language :: Python
Classifier: Framework :: Odoo
Classifier: Framework :: Odoo :: 16.0
Classifier: License :: OSI Approved :: GNU Affero General Public License v3
Requires-Python: >=3.10
Requires-Dist: odoo<16.1dev,>=16.0a
